applipy_http/__init__.py
applipy_http/api.py
applipy_http/config.py
applipy_http/cors.py
applipy_http/endpoint.py
applipy_http/module.py
applipy_http/path.py
applipy_http/py.typed
applipy_http/route.py
applipy_http/server.py
applipy_http/types.py
applipy_http/version.py
applipy_http/wrapper.py
tests/acceptance/__init__.py
tests/acceptance/common.py
tests/acceptance/test_applipy_http.py
applipy_http-2.2.1.dist-info/LICENSE
applipy_http-2.2.1.dist-info/METADATA
applipy_http-2.2.1.dist-info/WHEEL
applipy_http-2.2.1.dist-info/top_level.txt
applipy_http-2.2.1.dist-info/RECORD
