Metadata-Version: 2.1
Name: applipy_http
Version: 2.2.1
Summary: Library for building http services using applipy
Home-page: https://gitlab.com/applipy/applipy_http
Author: Alessio Linares
Author-email: mail@alessio.cc
License: Apache 2.0
Project-URL: Source, https://gitlab.com/applipy/applipy_http
Classifier: Development Status :: 5 - Production/Stable
Classifier: Intended Audience :: Developers
Classifier: License :: OSI Approved :: Apache Software License
Classifier: Programming Language :: Python :: 3.8
Classifier: Programming Language :: Python :: 3.9
Classifier: Topic :: Software Development :: Libraries
Requires-Python: >=3.8
License-File: LICENSE
Requires-Dist: applipy <3.0.0,>=2.0.0
Requires-Dist: aiohttp ~=3.8
Requires-Dist: aiohttp-cors ~=0.7
